{
  "id": "cd3fa8a1-c7db-440f-b8cb-a82af88b8287",
  "prevId": "00000000-0000-0000-0000-000000000000",
  "version": "7",
  "dialect": "postgresql",
  "tables": {
    "public.chart_of_accounts": {
      "name": "chart_of_accounts",
      "schema": "",
      "columns": {
        "id": {
          "name": "id",
          "type": "serial",
          "primaryKey": true,
          "notNull": true
        },
        "code": {
          "name": "code",
          "type": "varchar(20)",
          "primaryKey": false,
          "notNull": true
        },
        "name": {
          "name": "name",
          "type": "varchar(255)",
          "primaryKey": false,
          "notNull": true
        },
        "type": {
          "name": "type",
          "type": "varchar(50)",
          "primaryKey": false,
          "notNull": true
        },
        "parent_id": {
          "name": "parent_id",
          "type": "integer",
          "primaryKey": false,
          "notNull": false
        },
        "is_active": {
          "name": "is_active",
          "type": "boolean",
          "primaryKey": false,
          "notNull": false,
          "default": true
        },
        "created_at": {
          "name": "created_at",
          "type": "timestamp",
          "primaryKey": false,
          "notNull": false,
          "default": "now()"
        }
      },
      "indexes": {},
      "foreignKeys": {
        "chart_of_accounts_parent_id_chart_of_accounts_id_fk": {
          "name": "chart_of_accounts_parent_id_chart_of_accounts_id_fk",
          "tableFrom": "chart_of_accounts",
          "tableTo": "chart_of_accounts",
          "columnsFrom": [
            "parent_id"
          ],
          "columnsTo": [
            "id"
          ],
          "onDelete": "no action",
          "onUpdate": "no action"
        }
      },
      "compositePrimaryKeys": {},
      "uniqueConstraints": {
        "chart_of_accounts_code_unique": {
          "name": "chart_of_accounts_code_unique",
          "nullsNotDistinct": false,
          "columns": [
            "code"
          ]
        }
      },
      "policies": {},
      "checkConstraints": {},
      "isRLSEnabled": false
    },
    "public.contacts": {
      "name": "contacts",
      "schema": "",
      "columns": {
        "id": {
          "name": "id",
          "type": "serial",
          "primaryKey": true,
          "notNull": true
        },
        "type": {
          "name": "type",
          "type": "varchar(20)",
          "primaryKey": false,
          "notNull": true
        },
        "name": {
          "name": "name",
          "type": "varchar(255)",
          "primaryKey": false,
          "notNull": true
        },
        "email": {
          "name": "email",
          "type": "varchar(255)",
          "primaryKey": false,
          "notNull": false
        },
        "mobile": {
          "name": "mobile",
          "type": "varchar(20)",
          "primaryKey": false,
          "notNull": false
        },
        "address": {
          "name": "address",
          "type": "jsonb",
          "primaryKey": false,
          "notNull": false
        },
        "profile": {
          "name": "profile",
          "type": "jsonb",
          "primaryKey": false,
          "notNull": false
        },
        "is_active": {
          "name": "is_active",
          "type": "boolean",
          "primaryKey": false,
          "notNull": false,
          "default": true
        },
        "created_at": {
          "name": "created_at",
          "type": "timestamp",
          "primaryKey": false,
          "notNull": false,
          "default": "now()"
        },
        "updated_at": {
          "name": "updated_at",
          "type": "timestamp",
          "primaryKey": false,
          "notNull": false,
          "default": "now()"
        }
      },
      "indexes": {},
      "foreignKeys": {},
      "compositePrimaryKeys": {},
      "uniqueConstraints": {},
      "policies": {},
      "checkConstraints": {},
      "isRLSEnabled": false
    },
    "public.invoices": {
      "name": "invoices",
      "schema": "",
      "columns": {
        "id": {
          "name": "id",
          "type": "serial",
          "primaryKey": true,
          "notNull": true
        },
        "invoice_number": {
          "name": "invoice_number",
          "type": "varchar(50)",
          "primaryKey": false,
          "notNull": true
        },
        "type": {
          "name": "type",
          "type": "varchar(20)",
          "primaryKey": false,
          "notNull": true
        },
        "contact_id": {
          "name": "contact_id",
          "type": "integer",
          "primaryKey": false,
          "notNull": true
        },
        "order_id": {
          "name": "order_id",
          "type": "integer",
          "primaryKey": false,
          "notNull": false
        },
        "invoice_date": {
          "name": "invoice_date",
          "type": "timestamp",
          "primaryKey": false,
          "notNull": true
        },
        "due_date": {
          "name": "due_date",
          "type": "timestamp",
          "primaryKey": false,
          "notNull": false
        },
        "status": {
          "name": "status",
          "type": "varchar(20)",
          "primaryKey": false,
          "notNull": true,
          "default": "'UNPAID'"
        },
        "total_amount": {
          "name": "total_amount",
          "type": "numeric(12, 2)",
          "primaryKey": false,
          "notNull": false
        },
        "tax_amount": {
          "name": "tax_amount",
          "type": "numeric(12, 2)",
          "primaryKey": false,
          "notNull": false
        },
        "discount_amount": {
          "name": "discount_amount",
          "type": "numeric(12, 2)",
          "primaryKey": false,
          "notNull": false
        },
        "notes": {
          "name": "notes",
          "type": "text",
          "primaryKey": false,
          "notNull": false
        },
        "created_at": {
          "name": "created_at",
          "type": "timestamp",
          "primaryKey": false,
          "notNull": false,
          "default": "now()"
        },
        "updated_at": {
          "name": "updated_at",
          "type": "timestamp",
          "primaryKey": false,
          "notNull": false,
          "default": "now()"
        }
      },
      "indexes": {},
      "foreignKeys": {
        "invoices_contact_id_contacts_id_fk": {
          "name": "invoices_contact_id_contacts_id_fk",
          "tableFrom": "invoices",
          "tableTo": "contacts",
          "columnsFrom": [
            "contact_id"
          ],
          "columnsTo": [
            "id"
          ],
          "onDelete": "no action",
          "onUpdate": "no action"
        }
      },
      "compositePrimaryKeys": {},
      "uniqueConstraints": {
        "invoices_invoice_number_unique": {
          "name": "invoices_invoice_number_unique",
          "nullsNotDistinct": false,
          "columns": [
            "invoice_number"
          ]
        }
      },
      "policies": {},
      "checkConstraints": {},
      "isRLSEnabled": false
    },
    "public.order_items": {
      "name": "order_items",
      "schema": "",
      "columns": {
        "id": {
          "name": "id",
          "type": "serial",
          "primaryKey": true,
          "notNull": true
        },
        "order_id": {
          "name": "order_id",
          "type": "integer",
          "primaryKey": false,
          "notNull": true
        },
        "order_type": {
          "name": "order_type",
          "type": "varchar(20)",
          "primaryKey": false,
          "notNull": true
        },
        "product_id": {
          "name": "product_id",
          "type": "integer",
          "primaryKey": false,
          "notNull": true
        },
        "quantity": {
          "name": "quantity",
          "type": "numeric(10, 2)",
          "primaryKey": false,
          "notNull": true
        },
        "unit_price": {
          "name": "unit_price",
          "type": "numeric(10, 2)",
          "primaryKey": false,
          "notNull": true
        },
        "tax_amount": {
          "name": "tax_amount",
          "type": "numeric(10, 2)",
          "primaryKey": false,
          "notNull": false
        },
        "discount_amount": {
          "name": "discount_amount",
          "type": "numeric(10, 2)",
          "primaryKey": false,
          "notNull": false
        },
        "total_amount": {
          "name": "total_amount",
          "type": "numeric(10, 2)",
          "primaryKey": false,
          "notNull": false
        },
        "created_at": {
          "name": "created_at",
          "type": "timestamp",
          "primaryKey": false,
          "notNull": false,
          "default": "now()"
        }
      },
      "indexes": {},
      "foreignKeys": {
        "order_items_product_id_products_id_fk": {
          "name": "order_items_product_id_products_id_fk",
          "tableFrom": "order_items",
          "tableTo": "products",
          "columnsFrom": [
            "product_id"
          ],
          "columnsTo": [
            "id"
          ],
          "onDelete": "no action",
          "onUpdate": "no action"
        }
      },
      "compositePrimaryKeys": {},
      "uniqueConstraints": {},
      "policies": {},
      "checkConstraints": {},
      "isRLSEnabled": false
    },
    "public.payments": {
      "name": "payments",
      "schema": "",
      "columns": {
        "id": {
          "name": "id",
          "type": "serial",
          "primaryKey": true,
          "notNull": true
        },
        "invoice_id": {
          "name": "invoice_id",
          "type": "integer",
          "primaryKey": false,
          "notNull": true
        },
        "payment_date": {
          "name": "payment_date",
          "type": "timestamp",
          "primaryKey": false,
          "notNull": true
        },
        "amount": {
          "name": "amount",
          "type": "numeric(12, 2)",
          "primaryKey": false,
          "notNull": true
        },
        "payment_method": {
          "name": "payment_method",
          "type": "varchar(20)",
          "primaryKey": false,
          "notNull": true,
          "default": "'CASH'"
        },
        "reference": {
          "name": "reference",
          "type": "varchar(100)",
          "primaryKey": false,
          "notNull": false
        },
        "notes": {
          "name": "notes",
          "type": "text",
          "primaryKey": false,
          "notNull": false
        },
        "created_at": {
          "name": "created_at",
          "type": "timestamp",
          "primaryKey": false,
          "notNull": false,
          "default": "now()"
        }
      },
      "indexes": {},
      "foreignKeys": {
        "payments_invoice_id_invoices_id_fk": {
          "name": "payments_invoice_id_invoices_id_fk",
          "tableFrom": "payments",
          "tableTo": "invoices",
          "columnsFrom": [
            "invoice_id"
          ],
          "columnsTo": [
            "id"
          ],
          "onDelete": "no action",
          "onUpdate": "no action"
        }
      },
      "compositePrimaryKeys": {},
      "uniqueConstraints": {},
      "policies": {},
      "checkConstraints": {},
      "isRLSEnabled": false
    },
    "public.products": {
      "name": "products",
      "schema": "",
      "columns": {
        "id": {
          "name": "id",
          "type": "serial",
          "primaryKey": true,
          "notNull": true
        },
        "name": {
          "name": "name",
          "type": "varchar(255)",
          "primaryKey": false,
          "notNull": true
        },
        "type": {
          "name": "type",
          "type": "varchar(20)",
          "primaryKey": false,
          "notNull": true,
          "default": "'GOODS'"
        },
        "sales_price": {
          "name": "sales_price",
          "type": "numeric(10, 2)",
          "primaryKey": false,
          "notNull": false
        },
        "purchase_price": {
          "name": "purchase_price",
          "type": "numeric(10, 2)",
          "primaryKey": false,
          "notNull": false
        },
        "tax_percentage": {
          "name": "tax_percentage",
          "type": "numeric(5, 2)",
          "primaryKey": false,
          "notNull": false
        },
        "hsn_code": {
          "name": "hsn_code",
          "type": "varchar(20)",
          "primaryKey": false,
          "notNull": false
        },
        "category": {
          "name": "category",
          "type": "varchar(100)",
          "primaryKey": false,
          "notNull": false
        },
        "is_active": {
          "name": "is_active",
          "type": "boolean",
          "primaryKey": false,
          "notNull": false,
          "default": true
        },
        "created_at": {
          "name": "created_at",
          "type": "timestamp",
          "primaryKey": false,
          "notNull": false,
          "default": "now()"
        },
        "updated_at": {
          "name": "updated_at",
          "type": "timestamp",
          "primaryKey": false,
          "notNull": false,
          "default": "now()"
        }
      },
      "indexes": {},
      "foreignKeys": {},
      "compositePrimaryKeys": {},
      "uniqueConstraints": {},
      "policies": {},
      "checkConstraints": {},
      "isRLSEnabled": false
    },
    "public.purchase_orders": {
      "name": "purchase_orders",
      "schema": "",
      "columns": {
        "id": {
          "name": "id",
          "type": "serial",
          "primaryKey": true,
          "notNull": true
        },
        "po_number": {
          "name": "po_number",
          "type": "varchar(50)",
          "primaryKey": false,
          "notNull": true
        },
        "vendor_id": {
          "name": "vendor_id",
          "type": "integer",
          "primaryKey": false,
          "notNull": true
        },
        "order_date": {
          "name": "order_date",
          "type": "timestamp",
          "primaryKey": false,
          "notNull": true
        },
        "status": {
          "name": "status",
          "type": "varchar(20)",
          "primaryKey": false,
          "notNull": true,
          "default": "'DRAFT'"
        },
        "total_amount": {
          "name": "total_amount",
          "type": "numeric(12, 2)",
          "primaryKey": false,
          "notNull": false
        },
        "notes": {
          "name": "notes",
          "type": "text",
          "primaryKey": false,
          "notNull": false
        },
        "created_at": {
          "name": "created_at",
          "type": "timestamp",
          "primaryKey": false,
          "notNull": false,
          "default": "now()"
        },
        "updated_at": {
          "name": "updated_at",
          "type": "timestamp",
          "primaryKey": false,
          "notNull": false,
          "default": "now()"
        }
      },
      "indexes": {},
      "foreignKeys": {
        "purchase_orders_vendor_id_contacts_id_fk": {
          "name": "purchase_orders_vendor_id_contacts_id_fk",
          "tableFrom": "purchase_orders",
          "tableTo": "contacts",
          "columnsFrom": [
            "vendor_id"
          ],
          "columnsTo": [
            "id"
          ],
          "onDelete": "no action",
          "onUpdate": "no action"
        }
      },
      "compositePrimaryKeys": {},
      "uniqueConstraints": {
        "purchase_orders_po_number_unique": {
          "name": "purchase_orders_po_number_unique",
          "nullsNotDistinct": false,
          "columns": [
            "po_number"
          ]
        }
      },
      "policies": {},
      "checkConstraints": {},
      "isRLSEnabled": false
    },
    "public.sales_orders": {
      "name": "sales_orders",
      "schema": "",
      "columns": {
        "id": {
          "name": "id",
          "type": "serial",
          "primaryKey": true,
          "notNull": true
        },
        "so_number": {
          "name": "so_number",
          "type": "varchar(50)",
          "primaryKey": false,
          "notNull": true
        },
        "customer_id": {
          "name": "customer_id",
          "type": "integer",
          "primaryKey": false,
          "notNull": true
        },
        "order_date": {
          "name": "order_date",
          "type": "timestamp",
          "primaryKey": false,
          "notNull": true
        },
        "status": {
          "name": "status",
          "type": "varchar(20)",
          "primaryKey": false,
          "notNull": true,
          "default": "'DRAFT'"
        },
        "total_amount": {
          "name": "total_amount",
          "type": "numeric(12, 2)",
          "primaryKey": false,
          "notNull": false
        },
        "notes": {
          "name": "notes",
          "type": "text",
          "primaryKey": false,
          "notNull": false
        },
        "created_at": {
          "name": "created_at",
          "type": "timestamp",
          "primaryKey": false,
          "notNull": false,
          "default": "now()"
        },
        "updated_at": {
          "name": "updated_at",
          "type": "timestamp",
          "primaryKey": false,
          "notNull": false,
          "default": "now()"
        }
      },
      "indexes": {},
      "foreignKeys": {
        "sales_orders_customer_id_contacts_id_fk": {
          "name": "sales_orders_customer_id_contacts_id_fk",
          "tableFrom": "sales_orders",
          "tableTo": "contacts",
          "columnsFrom": [
            "customer_id"
          ],
          "columnsTo": [
            "id"
          ],
          "onDelete": "no action",
          "onUpdate": "no action"
        }
      },
      "compositePrimaryKeys": {},
      "uniqueConstraints": {
        "sales_orders_so_number_unique": {
          "name": "sales_orders_so_number_unique",
          "nullsNotDistinct": false,
          "columns": [
            "so_number"
          ]
        }
      },
      "policies": {},
      "checkConstraints": {},
      "isRLSEnabled": false
    },
    "public.taxes": {
      "name": "taxes",
      "schema": "",
      "columns": {
        "id": {
          "name": "id",
          "type": "serial",
          "primaryKey": true,
          "notNull": true
        },
        "name": {
          "name": "name",
          "type": "varchar(100)",
          "primaryKey": false,
          "notNull": true
        },
        "computation": {
          "name": "computation",
          "type": "varchar(20)",
          "primaryKey": false,
          "notNull": true,
          "default": "'PERCENTAGE'"
        },
        "applicable_on": {
          "name": "applicable_on",
          "type": "varchar(20)",
          "primaryKey": false,
          "notNull": true,
          "default": "'SALES'"
        },
        "rate": {
          "name": "rate",
          "type": "numeric(5, 2)",
          "primaryKey": false,
          "notNull": true
        },
        "is_active": {
          "name": "is_active",
          "type": "boolean",
          "primaryKey": false,
          "notNull": false,
          "default": true
        },
        "created_at": {
          "name": "created_at",
          "type": "timestamp",
          "primaryKey": false,
          "notNull": false,
          "default": "now()"
        }
      },
      "indexes": {},
      "foreignKeys": {},
      "compositePrimaryKeys": {},
      "uniqueConstraints": {},
      "policies": {},
      "checkConstraints": {},
      "isRLSEnabled": false
    },
    "public.transactions": {
      "name": "transactions",
      "schema": "",
      "columns": {
        "id": {
          "name": "id",
          "type": "serial",
          "primaryKey": true,
          "notNull": true
        },
        "date": {
          "name": "date",
          "type": "timestamp",
          "primaryKey": false,
          "notNull": true
        },
        "description": {
          "name": "description",
          "type": "text",
          "primaryKey": false,
          "notNull": true
        },
        "debit_account_id": {
          "name": "debit_account_id",
          "type": "integer",
          "primaryKey": false,
          "notNull": false
        },
        "credit_account_id": {
          "name": "credit_account_id",
          "type": "integer",
          "primaryKey": false,
          "notNull": false
        },
        "amount": {
          "name": "amount",
          "type": "numeric(12, 2)",
          "primaryKey": false,
          "notNull": true
        },
        "reference": {
          "name": "reference",
          "type": "varchar(100)",
          "primaryKey": false,
          "notNull": false
        },
        "created_at": {
          "name": "created_at",
          "type": "timestamp",
          "primaryKey": false,
          "notNull": false,
          "default": "now()"
        }
      },
      "indexes": {},
      "foreignKeys": {
        "transactions_debit_account_id_chart_of_accounts_id_fk": {
          "name": "transactions_debit_account_id_chart_of_accounts_id_fk",
          "tableFrom": "transactions",
          "tableTo": "chart_of_accounts",
          "columnsFrom": [
            "debit_account_id"
          ],
          "columnsTo": [
            "id"
          ],
          "onDelete": "no action",
          "onUpdate": "no action"
        },
        "transactions_credit_account_id_chart_of_accounts_id_fk": {
          "name": "transactions_credit_account_id_chart_of_accounts_id_fk",
          "tableFrom": "transactions",
          "tableTo": "chart_of_accounts",
          "columnsFrom": [
            "credit_account_id"
          ],
          "columnsTo": [
            "id"
          ],
          "onDelete": "no action",
          "onUpdate": "no action"
        }
      },
      "compositePrimaryKeys": {},
      "uniqueConstraints": {},
      "policies": {},
      "checkConstraints": {},
      "isRLSEnabled": false
    },
    "public.users": {
      "name": "users",
      "schema": "",
      "columns": {
        "id": {
          "name": "id",
          "type": "serial",
          "primaryKey": true,
          "notNull": true
        },
        "email": {
          "name": "email",
          "type": "varchar(255)",
          "primaryKey": false,
          "notNull": true
        },
        "name": {
          "name": "name",
          "type": "varchar(255)",
          "primaryKey": false,
          "notNull": false
        },
        "password": {
          "name": "password",
          "type": "text",
          "primaryKey": false,
          "notNull": false
        },
        "role": {
          "name": "role",
          "type": "varchar(50)",
          "primaryKey": false,
          "notNull": true,
          "default": "'ACCOUNTANT'"
        },
        "is_active": {
          "name": "is_active",
          "type": "boolean",
          "primaryKey": false,
          "notNull": false,
          "default": true
        },
        "created_at": {
          "name": "created_at",
          "type": "timestamp",
          "primaryKey": false,
          "notNull": false,
          "default": "now()"
        },
        "updated_at": {
          "name": "updated_at",
          "type": "timestamp",
          "primaryKey": false,
          "notNull": false,
          "default": "now()"
        }
      },
      "indexes": {},
      "foreignKeys": {},
      "compositePrimaryKeys": {},
      "uniqueConstraints": {
        "users_email_unique": {
          "name": "users_email_unique",
          "nullsNotDistinct": false,
          "columns": [
            "email"
          ]
        }
      },
      "policies": {},
      "checkConstraints": {},
      "isRLSEnabled": false
    }
  },
  "enums": {},
  "schemas": {},
  "sequences": {},
  "roles": {},
  "policies": {},
  "views": {},
  "_meta": {
    "columns": {},
    "schemas": {},
    "tables": {}
  }
}